sponfiss/__init__.py
sponfiss/snsfpy.py
sponfiss-0.0.1.dist-info/METADATA
sponfiss-0.0.1.dist-info/WHEEL
sponfiss-0.0.1.dist-info/top_level.txt
sponfiss-0.0.1.dist-info/RECORD
