Metadata-Version: 2.4
Name: sponfiss
Version: 0.0.1
Requires-Dist: numpy
Dynamic: requires-dist
